noquant-futu/VERSION.txt
noquant-futu/__init__.py
noquant-futu/common/__init__.py
noquant-futu/common/callback_executor.py
noquant-futu/common/comm_add_path.py
noquant-futu/common/conn_key.txt
noquant-futu/common/conn_mng.py
noquant-futu/common/constant.py
noquant-futu/common/diag.py
noquant-futu/common/err.py
noquant-futu/common/ft_logger.py
noquant-futu/common/handler_context.py
noquant-futu/common/network_manager.py
noquant-futu/common/open_context_base.py
noquant-futu/common/pbjson.py
noquant-futu/common/sys_config.py
noquant-futu/common/utils.py
noquant-futu/common/pb/Common.proto
noquant-futu/common/pb/Common_pb2.py
noquant-futu/common/pb/GetDelayStatistics.proto
noquant-futu/common/pb/GetDelayStatistics_pb2.py
noquant-futu/common/pb/GetGlobalState.proto
noquant-futu/common/pb/GetGlobalState_pb2.py
noquant-futu/common/pb/GetUserInfo.proto
noquant-futu/common/pb/GetUserInfo_pb2.py
noquant-futu/common/pb/InitConnect.proto
noquant-futu/common/pb/InitConnect_pb2.py
noquant-futu/common/pb/KeepAlive.proto
noquant-futu/common/pb/KeepAlive_pb2.py
noquant-futu/common/pb/Notify.proto
noquant-futu/common/pb/Notify_pb2.py
noquant-futu/common/pb/Qot_Common.proto
noquant-futu/common/pb/Qot_Common_pb2.py
noquant-futu/common/pb/Qot_GetBasicQot.proto
noquant-futu/common/pb/Qot_GetBasicQot_pb2.py
noquant-futu/common/pb/Qot_GetBroker.proto
noquant-futu/common/pb/Qot_GetBroker_pb2.py
noquant-futu/common/pb/Qot_GetCapitalDistribution.proto
noquant-futu/common/pb/Qot_GetCapitalDistribution_pb2.py
noquant-futu/common/pb/Qot_GetCapitalFlow.proto
noquant-futu/common/pb/Qot_GetCapitalFlow_pb2.py
noquant-futu/common/pb/Qot_GetCodeChange.proto
noquant-futu/common/pb/Qot_GetCodeChange_pb2.py
noquant-futu/common/pb/Qot_GetFutureInfo.proto
noquant-futu/common/pb/Qot_GetFutureInfo_pb2.py
noquant-futu/common/pb/Qot_GetHistoryKL.proto
noquant-futu/common/pb/Qot_GetHistoryKLPoints.proto
noquant-futu/common/pb/Qot_GetHistoryKLPoints_pb2.py
noquant-futu/common/pb/Qot_GetHistoryKL_pb2.py
noquant_futu-5.10.2208.dist-info/METADATA
noquant_futu-5.10.2208.dist-info/WHEEL
noquant_futu-5.10.2208.dist-info/top_level.txt
noquant_futu-5.10.2208.dist-info/RECORD
