Metadata-Version: 2.1
Name: noquant-futu
Version: 5.10.2208
Summary: Futu Quantitative Trading API Of Noquant
Home-page: UNKNOWN
Author: hackmong
Author-email: hackmong@163.com
License: Apache License 2.0
Platform: UNKNOWN
Requires-Dist: pandas
Requires-Dist: simplejson
Requires-Dist: protobuf (==3.5.1)
Requires-Dist: PyCryptodome
